pahud_cdktf_aws_ecs/__init__.py
pahud_cdktf_aws_ecs/py.typed
pahud_cdktf_aws_ecs/_jsii/__init__.py
pahud_cdktf_aws_ecs/_jsii/cdktf-aws-ecs@0.1.92.jsii.tgz
pahud_cdktf_aws_ecs-0.1.92.dist-info/LICENSE
pahud_cdktf_aws_ecs-0.1.92.dist-info/METADATA
pahud_cdktf_aws_ecs-0.1.92.dist-info/WHEEL
pahud_cdktf_aws_ecs-0.1.92.dist-info/top_level.txt
pahud_cdktf_aws_ecs-0.1.92.dist-info/RECORD
