Metadata-Version: 2.1
Name: pahud-cdktf-aws-ecs
Version: 0.1.92
Summary: CDKTF construct library for Amazon ECS
Home-page: https://github.com/pahud/cdktf-aws-ecs
Author: Pahud Hsieh<pahudnet@gmail.com>
License: Apache-2.0
Project-URL: Source, https://github.com/pahud/cdktf-aws-ecs
Platform: UNKNOWN
Classifier: Intended Audience :: Developers
Classifier: Operating System :: OS Independent
Classifier: Programming Language :: JavaScript
Classifier: Programming Language :: Python :: 3 :: Only
Classifier: Programming Language :: Python :: 3.6
Classifier: Programming Language :: Python :: 3.7
Classifier: Programming Language :: Python :: 3.8
Classifier: Programming Language :: Python :: 3.9
Classifier: Typing :: Typed
Classifier: Development Status :: 5 - Production/Stable
Classifier: License :: OSI Approved
Requires-Python: >=3.6
License-File: LICENSE
Requires-Dist: cdktf-cdktf-provider-aws (<3.0.0,>=2.0.13)
Requires-Dist: cdktf (<0.8.0,>=0.7.0)
Requires-Dist: constructs (<11.0.0,>=10.0.0)
Requires-Dist: jsii (<2.0.0,>=1.46.0)
Requires-Dist: publication (>=0.0.3)
